{
    "calendar": "noleap",
    "coords": "{'lat', 'time', 'lon'}",
    "end_date": "2005-12-16 12:00:00",
    "ensemble": "r1i1p1",
    "experiment_id": "historical",
    "frequency": "mon",
    "institute_id": "IPSL",
    "lat_max": "90.0",
    "lat_min": "-90.0",
    "lon_max": "356.25",
    "lon_min": "0.0",
    "long_name": "Carbon Mass Flux into Atmosphere due to Heterotrophic Respiration on Land",
    "max_value": "nan",
    "min_value": "nan",
    "model_id": "IPSL-CM5B-LR",
    "modeling_realm": "land",
    "project_id": "CMIP5",
    "shape": [
        2196,
        96,
        96
    ],
    "standard_name": "heterotrophic_respiration_carbon_flux",
    "start_date": "1850-01-16 12:00:00",
    "table_id": "Lmon",
    "time_axis_length": 2196,
    "time_long_name": "time",
    "time_standard_name": "time",
    "units": "kg m-2 s-1",
    "variable": "rh"
}